{"cameraMode":{"drawMode":0,"name":"Shaded","section":"Shading Mode"},"sceneLighting":true,"audioPlay":false,"sceneViewState":{"showFog":true,"showMaterialUpdate":false,"showSkybox":true,"showFlares":true,"showImageEffects":true,"showParticleSystems":true,"showVisualEffectGraphs":true,"m_FxEnabled":true},"in2DMode":false,"pivot":{"x":52.1156120300293,"y":3.058488368988037,"z":8.69096851348877},"rotation":{"x":0.06504471600055695,"y":-0.8926705121994019,"z":0.1333753913640976,"w":0.42762643098831179},"size":1.101312279701233,"orthographic":false}